hotmodern_python/__init__.py
hotmodern_python/console.py
hotmodern_python/wikipedia.py
hotmodern_python-0.1.2.dist-info/LICENSE
hotmodern_python-0.1.2.dist-info/METADATA
hotmodern_python-0.1.2.dist-info/WHEEL
hotmodern_python-0.1.2.dist-info/entry_points.txt
hotmodern_python-0.1.2.dist-info/RECORD
