Metadata-Version: 2.1
Name: hotmodern-python
Version: 0.1.2
Summary: Python learning project by blog posts series 'Hypermodern Python' (by Claudio Jolowicz)
Home-page: https://github.com/hotenov/hotmodern-python
Keywords: hypermodern
Author: Artem Hotenov
Author-email: artem@hotenov.com
Requires-Python: >=3.11,<4.0
Classifier: Programming Language :: Python :: 3
Classifier: Programming Language :: Python :: 3.11
Classifier: Programming Language :: Python :: 3.12
Requires-Dist: click (>=8.1.7,<9.0.0)
Requires-Dist: desert (>=2022.9.22,<2023.0.0)
Requires-Dist: marshmallow (>=3.10.0,<4.0.0)
Requires-Dist: requests (>=2.32.3,<3.0.0)
Project-URL: Documentation, https://hotmodern-python.readthedocs.io
Project-URL: Repository, https://github.com/hotenov/hotmodern-python
